[
  {
    "race_id": 3,
    "capacity_ccm": 1000,
    "description": "",
    "mechanic_id": 4,
    "type": "Stadtwagen",
    "year": 1990,
    "driver_id": 3,
    "passenger_id": 2,
    "id": 1,
    "owner_id": 2,
    "category_id": 2,
    "power_kw": 1000,
    "brand": "Audi"
  },
  {
    "race_id": 3,
    "capacity_ccm": 2000,
    "description": "",
    "mechanic_id": 2,
    "type": "Kleinwagen",
    "year": 1991,
    "driver_id": 3,
    "passenger_id": 4,
    "id": 2,
    "owner_id": 2,
    "category_id": 2,
    "power_kw": 2000,
    "brand": "Smart"
  },
  {
    "race_id": 4,
    "capacity_ccm": 500,
    "description": "",
    "mechanic_id": 4,
    "type": "Klapperkiste",
    "year": 1960,
    "driver_id": 3,
    "passenger_id": 2,
    "id": 3,
    "owner_id": 3,
    "category_id": 2,
    "power_kw": 1,
    "brand": "BWM"
  },
  {
    "race_id": 1,
    "capacity_ccm": 123,
    "description": "",
    "mechanic_id": 4,
    "type": "Kleintraktor",
    "year": 1930,
    "driver_id": 3,
    "passenger_id": 2,
    "id": 4,
    "owner_id": 3,
    "category_id": 1,
    "power_kw": 123,
    "brand": "Alpenland"
  },
  {
    "race_id": 1,
    "capacity_ccm": 3000,
    "description": "",
    "mechanic_id": 2,
    "type": "Gel\u00e4ndewagen",
    "year": 1994,
    "driver_id": 4,
    "passenger_id": 3,
    "id": 5,
    "owner_id": 4,
    "category_id": 2,
    "power_kw": 75,
    "brand": "Suzuki"
  },
  {
    "race_id": 0,
    "capacity_ccm": 10000,
    "description": "",
    "mechanic_id": 2,
    "type": "Kamikaze",
    "year": 1994,
    "driver_id": 4,
    "passenger_id": 3,
    "id": 6,
    "owner_id": 4,
    "category_id": 2,
    "power_kw": 10000,
    "brand": "Ferrari"
  },
  {
    "race_id": 1,
    "capacity_ccm": 1000,
    "description": "",
    "mechanic_id": 2,
    "type": "Traktor",
    "year": 1990,
    "driver_id": 3,
    "passenger_id": 4,
    "id": 7,
    "owner_id": 4,
    "category_id": 1,
    "power_kw": 100,
    "brand": "Agria"
  },
  {
    "race_id": 2,
    "capacity_ccm": 1,
    "description": "",
    "mechanic_id": 5,
    "type": "1",
    "year": 1111,
    "driver_id": 5,
    "passenger_id": 5,
    "id": 8,
    "owner_id": 5,
    "category_id": 1,
    "power_kw": 1,
    "brand": "Demotraktor"
  },
  {
    "race_id": 2,
    "capacity_ccm": 1,
    "description": "",
    "mechanic_id": 5,
    "type": "2",
    "year": 1,
    "driver_id": 5,
    "passenger_id": 5,
    "id": 9,
    "owner_id": 5,
    "category_id": 1,
    "power_kw": 1,
    "brand": "Demotraktor"
  },
  {
    "race_id": 2,
    "capacity_ccm": 1,
    "description": "",
    "mechanic_id": 5,
    "type": "3",
    "year": 1,
    "driver_id": 5,
    "passenger_id": 5,
    "id": 10,
    "owner_id": 5,
    "category_id": 1,
    "power_kw": 1,
    "brand": "Demotraktor"
  },
  {
    "race_id": 1,
    "capacity_ccm": 1,
    "description": "",
    "mechanic_id": 5,
    "type": "4",
    "year": 1,
    "driver_id": 5,
    "passenger_id": 5,
    "id": 11,
    "owner_id": 5,
    "category_id": 1,
    "power_kw": 1,
    "brand": "Demotraktor"
  },
  {
    "race_id": 2,
    "capacity_ccm": 1,
    "description": "",
    "mechanic_id": 5,
    "type": "1",
    "year": 1,
    "driver_id": 5,
    "passenger_id": 5,
    "id": 12,
    "owner_id": 5,
    "category_id": 2,
    "power_kw": 1,
    "brand": "Democabrio"
  },
  {
    "race_id": 2,
    "capacity_ccm": 1,
    "description": "",
    "mechanic_id": 5,
    "type": "2",
    "year": 1,
    "driver_id": 5,
    "passenger_id": 5,
    "id": 13,
    "owner_id": 5,
    "category_id": 2,
    "power_kw": 1,
    "brand": "Democabrio"
  },
  {
    "race_id": 0,
    "capacity_ccm": 1,
    "description": "",
    "mechanic_id": 5,
    "type": "3",
    "year": 1,
    "driver_id": 5,
    "passenger_id": 5,
    "id": 14,
    "owner_id": 5,
    "category_id": 2,
    "power_kw": 1,
    "brand": "Democabrio"
  }
]